asymmetric/__init__.py
asymmetric/callbacks/__init__.py
asymmetric/callbacks/callback_object.py
asymmetric/callbacks/core.py
asymmetric/callbacks/utils.py
asymmetric/cli/__init__.py
asymmetric/cli/core.py
asymmetric/cli/helpers.py
asymmetric/cli/utils.py
asymmetric/constants.py
asymmetric/core.py
asymmetric/endpoints.py
asymmetric/errors.py
asymmetric/helpers.py
asymmetric/loggers.py
asymmetric/openapi/__init__.py
asymmetric/openapi/constants.py
asymmetric/openapi/core.py
asymmetric/openapi/docs.py
asymmetric/openapi/helpers.py
asymmetric/singleton.py
asymmetric/utils.py
asymmetric-0.3.0.dist-info/entry_points.txt
asymmetric-0.3.0.dist-info/LICENSE
asymmetric-0.3.0.dist-info/WHEEL
asymmetric-0.3.0.dist-info/METADATA
asymmetric-0.3.0.dist-info/RECORD
