Metadata-Version: 2.1
Name: asymmetric
Version: 0.3.0
Summary: The async framework that calls you back! Enable ridiculously fast and easy module-to-API transformations. Learn in minutes, implement in seconds. Batteries included.
Home-page: https://asymmetric.one/
License: MIT
Author: Daniel Leal
Author-email: dlleal@uc.cl
Maintainer: Daniel Leal
Maintainer-email: dlleal@uc.cl
Requires-Python: >=3.6,<4.0
Classifier: Environment :: Web Environment
Classifier: Intended Audience :: Developers
Classifier: License :: OSI Approved :: MIT License
Classifier: Operating System :: OS Independent
Classifier: Programming Language :: Python
Classifier: Programming Language :: Python :: 3
Classifier: Programming Language :: Python :: 3.6
Classifier: Programming Language :: Python :: 3.7
Classifier: Programming Language :: Python :: 3.8
Classifier: Programming Language :: Python :: 3.9
Classifier: Topic :: Internet :: WWW/HTTP :: Dynamic Content
Classifier: Topic :: Software Development :: Libraries :: Application Frameworks
Classifier: Topic :: Software Development :: Libraries :: Python Modules
Requires-Dist: httpx (>=0.16.1,<0.17.0)
Requires-Dist: starlette (>=0.13.8,<0.14.0)
Requires-Dist: uvicorn (>=0.12.2,<0.13.0)
Project-URL: Documentation, https://asymmetric.one/docs/
Project-URL: Issue Tracker, https://github.com/daleal/asymmetric/issues
Project-URL: Repository, https://github.com/daleal/asymmetric
